{
	"name": "ETL_LKP_SEXO_CAR",
	"properties": {
		"activities": [
			{
				"name": "COPY_TO_STAGE",
				"type": "Copy",
				"dependsOn": [],
				"policy": {
					"timeout": "0.12:00:00",
					"retry": 0,
					"retryIntervalInSeconds": 30,
					"secureOutput": false,
					"secureInput": false
				},
				"userProperties": [],
				"typeProperties": {
					"source": {
						"type": "ExcelSource",
						"storeSettings": {
							"type": "AzureBlobStorageReadSettings",
							"recursive": true,
							"enablePartitionDiscovery": false
						}
					},
					"sink": {
						"type": "AzureSqlSink",
						"writeBehavior": "insert",
						"sqlWriterUseTableLock": false
					},
					"enableStaging": false,
					"translator": {
						"type": "TabularTranslator",
						"mappings": [
							{
								"source": {
									"name": "ID_SEXO",
									"type": "String",
									"physicalType": "String"
								},
								"sink": {
									"name": "CD_SEXO",
									"type": "String",
									"physicalType": "char"
								}
							},
							{
								"source": {
									"name": "NM_SEXO",
									"type": "String",
									"physicalType": "String"
								},
								"sink": {
									"name": "NM_SEXO",
									"type": "String",
									"physicalType": "varchar"
								}
							}
						],
						"typeConversion": true,
						"typeConversionSettings": {
							"allowDataTruncation": true,
							"treatBooleanAsNumber": false
						}
					}
				},
				"inputs": [
					{
						"referenceName": "DATA_GENDER",
						"type": "DatasetReference"
					}
				],
				"outputs": [
					{
						"referenceName": "STG_TBL_GENDER",
						"type": "DatasetReference"
					}
				]
			}
		],
		"annotations": [],
		"lastPublishTime": "2022-10-21T21:07:00Z"
	},
	"type": "Microsoft.DataFactory/factories/pipelines"
}